rsaitehu/ransaccuda.py
rsaitehu_ransaccuda-0.0.2.dist-info/METADATA
rsaitehu_ransaccuda-0.0.2.dist-info/WHEEL
rsaitehu_ransaccuda-0.0.2.dist-info/top_level.txt
rsaitehu_ransaccuda-0.0.2.dist-info/RECORD
